Metadata-Version: 2.1
Name: xia-logger-pubsub
Version: 0.1.5
Home-page: https://develop.x-i-a.com/docs/xia-logger-pubsub/0.1.5/index.html
Author: X-I-A
Author-email: admin@x-i-a.com
Requires-Python: >=3.9
License-File: LICENSE.txt
Requires-Dist: google-cloud-pubsub
Requires-Dist: xia-logger
